datasette_render_markdown/__init__.py
datasette_render_markdown-2.2.1.dist-info/LICENSE
datasette_render_markdown-2.2.1.dist-info/METADATA
datasette_render_markdown-2.2.1.dist-info/WHEEL
datasette_render_markdown-2.2.1.dist-info/entry_points.txt
datasette_render_markdown-2.2.1.dist-info/top_level.txt
datasette_render_markdown-2.2.1.dist-info/RECORD
