Metadata-Version: 2.1
Name: datasette-render-markdown
Version: 2.2.1
Summary: Datasette plugin for rendering Markdown
Home-page: https://github.com/simonw/datasette-render-markdown
Author: Simon Willison
License: Apache License, Version 2.0
Requires-Python: >=3.7
License-File: LICENSE
Requires-Dist: datasette
Requires-Dist: markdown
Requires-Dist: bleach
Provides-Extra: test
Requires-Dist: pytest ; extra == 'test'
Requires-Dist: pytest-asyncio ; extra == 'test'
